README.md
setup.cfg
setup.py
ie_mbdbl2018_salibt/__init__.py
ie_mbdbl2018_salibt/ie_mbdbl2018_salibt.py
ie_mbdbl2018_salibt.egg-info/PKG-INFO
ie_mbdbl2018_salibt.egg-info/SOURCES.txt
ie_mbdbl2018_salibt.egg-info/dependency_links.txt
ie_mbdbl2018_salibt.egg-info/not-zip-safe
ie_mbdbl2018_salibt.egg-info/top_level.txt